cameraman/__init__.py
cameraman/cameraman.py
cameraman/helpers.py
cameraman/cli/__init__.py
cameraman/cli/config.py
cameraman/cli/inventory.py
cameraman/cli/main.py
cameraman/cli/setup.py
cameraman/cli/wingdbstub.py
cameraman/cli/workspace.py
cameraman-0.1.11.dist-info/AUTHORS.rst
cameraman-0.1.11.dist-info/LICENSE
cameraman-0.1.11.dist-info/METADATA
cameraman-0.1.11.dist-info/WHEEL
cameraman-0.1.11.dist-info/entry_points.txt
cameraman-0.1.11.dist-info/top_level.txt
cameraman-0.1.11.dist-info/RECORD
