Metadata-Version: 2.1
Name: cameraman
Version: 0.1.11
Summary: Camera Control Utility
Home-page: https://github.com/asterio/cameraman
Author: Asterio Gonzalez
Author-email: apastor@cibernos.com
Keywords: cameraman
Classifier: Development Status :: 2 - Pre-Alpha
Classifier: Intended Audience :: Developers
Classifier: Natural Language :: English
Classifier: Programming Language :: Python :: 3
Classifier: Programming Language :: Python :: 3.9
Classifier: Programming Language :: Python :: 3.10
Classifier: Programming Language :: Python :: 3.11
Requires-Python: >=3.6
License-File: LICENSE
License-File: AUTHORS.rst
Requires-Dist: Click >=7.1.2
Requires-Dist: glom
Requires-Dist: jmespath
Requires-Dist: pycelium >=0.1.37
